common/__init__.py
common_francis/__init__.py
common_francis/annotation/__init__.py
common_francis/annotation/design_patterns.py
common_francis/log/Logger.py
common_francis/log/__init__.py
common_francis_francis95_han-0.0.1.dist-info/LICENSE
common_francis_francis95_han-0.0.1.dist-info/METADATA
common_francis_francis95_han-0.0.1.dist-info/WHEEL
common_francis_francis95_han-0.0.1.dist-info/top_level.txt
common_francis_francis95_han-0.0.1.dist-info/RECORD
