Metadata-Version: 2.1
Name: common-francis-francis95-han
Version: 0.0.1
Summary: python common_francis package
Home-page: https://github.com/francis95-han/common-francis95-han
Author: francis95-han
Author-email: zhangbohan.dell@gmail.com
License: MIT
Platform: UNKNOWN
Classifier: Topic :: Utilities
Classifier: Programming Language :: Python
Classifier: Programming Language :: Python :: 3
Classifier: Programming Language :: Python :: 3.6
Classifier: Programming Language :: Python :: 3.7
